lusid/__init__.py
lusid/__version__.py
lusid/api_client.py
lusid/configuration.py
lusid/exceptions.py
lusid/rest.py
lusid/api/__init__.py
lusid/api/aggregation_api.py
lusid/api/allocations_api.py
lusid/api/application_metadata_api.py
lusid/api/blocks_api.py
lusid/api/calendars_api.py
lusid/api/complex_market_data_api.py
lusid/api/compliance_api.py
lusid/api/configuration_recipe_api.py
lusid/api/conventions_api.py
lusid/api/corporate_action_sources_api.py
lusid/api/counterparties_api.py
lusid/api/custom_entities_api.py
lusid/api/custom_entity_definitions_api.py
lusid/api/cut_label_definitions_api.py
lusid/api/data_types_api.py
lusid/api/derived_transaction_portfolios_api.py
lusid/api/entities_api.py
lusid/api/executions_api.py
lusid/api/fees_and_commissions_api.py
lusid/api/instruments_api.py
lusid/api/legal_entities_api.py
lusid/api/order_graph_api.py
lusid/api/order_instructions_api.py
lusid/api/orders_api.py
lusid/api/packages_api.py
lusid/api/participations_api.py
lusid/api/persons_api.py
lusid/api/placements_api.py
lusid/api/portfolio_groups_api.py
lusid/api/portfolios_api.py
lusid/api/property_definitions_api.py
lusid/api/quotes_api.py
lusid/api/reconciliations_api.py
lusid/api/reference_portfolio_api.py
lusid/api/relation_definitions_api.py
lusid/api/relations_api.py
lusid/api/relationship_definitions_api.py
lusid/api/relationships_api.py
lusid/api/schemas_api.py
lusid/api/scopes_api.py
lusid/api/search_api.py
lusid/api/sequences_api.py
lusid/api/structured_result_data_api.py
lusid/api/system_configuration_api.py
lusid/api/transaction_configuration_api.py
lusid/api/transaction_fees_api.py
lusid/api/transaction_portfolios_api.py
lusid/api/translation_api.py
lusid/models/__init__.py
lusid/models/a2_b_breakdown.py
lusid/models/a2_b_category.py
lusid/models/a2_b_data_record.py
lusid/models/a2_b_movement_record.py
lusid/models/access_controlled_action.py
lusid/models/access_controlled_resource.py
lusid/models/access_metadata_value.py
lusid_sdk_generated_preview-0.11.4449.dist-info/METADATA
lusid_sdk_generated_preview-0.11.4449.dist-info/WHEEL
lusid_sdk_generated_preview-0.11.4449.dist-info/top_level.txt
lusid_sdk_generated_preview-0.11.4449.dist-info/RECORD
